README.rst
setup.py
pyEOF/__init__.py
pyEOF/pyEOF.py
pyEOF.egg-info/PKG-INFO
pyEOF.egg-info/SOURCES.txt
pyEOF.egg-info/dependency_links.txt
pyEOF.egg-info/requires.txt
pyEOF.egg-info/top_level.txt
pyEOF/util/__init__.py
pyEOF/util/advanced_pca/__init__.py
pyEOF/util/advanced_pca/custom_pca.py