Metadata-Version: 1.1
Name: pyEOF
Version: 0.0.0
Summary: Empirical Orthogonal Function (EOF) analysis and Rotated EOF analysis in Python
Home-page: https://github.com/zzheng93/pyEOF
Author: Zhonghua Zheng
Author-email: zhonghua.zheng@outlook.com
License: MIT
Platform: UNKNOWN
Classifier: Development Status :: 2 - Pre-Alpha
Classifier: Intended Audience :: Science/Research
Classifier: License :: OSI Approved :: MIT License
Classifier: Natural Language :: English
Classifier: Operating System :: OS Independent
Classifier: Programming Language :: Python :: 3
Classifier: Topic :: Scientific/Engineering :: Atmospheric Science
